LICENSE
proxygrab/__init__.py
proxygrab/cmdline.py
proxygrab/package/__init__.py
proxygrab/package/_utils.py
proxygrab/package/api/__init__.py
proxygrab/package/api/proxylist.py
proxygrab/package/api/proxyscrape.py
proxygrab/package/errors.py
proxygrab/package/main.py
proxygrab/package/scrappers/__init__.py
proxygrab/package/scrappers/free_proxy_list.py
proxygrab/package/scrappers/github.py
proxygrab/package/scrappers/socks_proxy.py
proxygrab/package/scrappers/sslproxies.py
proxygrab/package/scrappers/us_proxy.py
proxygrab-1.2.9.dist-info/entry_points.txt
proxygrab-1.2.9.dist-info/LICENSE
proxygrab-1.2.9.dist-info/WHEEL
proxygrab-1.2.9.dist-info/METADATA
proxygrab-1.2.9.dist-info/RECORD
