Metadata-Version: 2.1
Name: proxygrab
Version: 1.2.9
Summary: Asynchronous Library to scrap proxies for my web scrapping applications and other testing purposes
Home-page: https://github.com/Divkix/ProxyGrab
License: MIT
Keywords: proxygrab,proxy scrapper,proxy grabber
Author: Divkix
Author-email: techdroidroot@gmail.com
Requires-Python: >=3.7,<4.0
Classifier: Development Status :: 5 - Production/Stable
Classifier: Environment :: Console
Classifier: License :: OSI Approved :: MIT License
Classifier: Natural Language :: English
Classifier: Operating System :: OS Independent
Classifier: Programming Language :: Python :: 3
Classifier: Programming Language :: Python :: 3.7
Classifier: Programming Language :: Python :: 3.8
Classifier: Programming Language :: Python :: 3.9
Classifier: Programming Language :: Python :: 3.10
Classifier: Programming Language :: Python :: 3
Classifier: Programming Language :: Python :: Implementation :: CPython
Classifier: Topic :: Software Development :: Libraries
Classifier: Topic :: Software Development :: Libraries :: Python Modules
Classifier: Topic :: Utilities
Requires-Dist: aiodns (>=3.0.0,<4.0.0)
Requires-Dist: aiohttp (>=3.8.1,<4.0.0)
Requires-Dist: beautifulsoup4 (>=4.10.0,<5.0.0)
Requires-Dist: cchardet (>=2.1.7,<3.0.0)
Requires-Dist: click (>=8.1.2,<9.0.0)
Requires-Dist: lxml (>=4.8.0,<5.0.0)
Requires-Dist: ujson (>=5.1.0,<6.0.0)
Project-URL: Bug Tracker, https://github.com/Divkix/ProxyGrab/issues
Project-URL: Community, https://t.me/DivideProjects
Project-URL: Documentation, https://proxygrab.divkix.me
Project-URL: Repository, https://github.com/Divkix/ProxyGrab
